{
  "number": "11463",
  "name": "Somnath-Jabalpur Express",
  "type": "Exp",
  "source": "SOMNATH",
  "sourceCode": "SMNH",
  "destination": "JABALPUR",
  "destinationCode": "JBP",
  "departureTime": "09:40:00",
  "arrivalTime": "15:10:00",
  "duration": "29h 30m",
  "distance": "1415 km",
  "runningDays": [
    "Mon",
    "Tue",
    "Wed",
    "Thu",
    "Fri",
    "Sat",
    "Sun"
  ],
  "zone": "CR",
  "classes": [
    "3A",
    "2A",
    "SL"
  ],
  "stops": 0,
  "majorStops": [],
  "frequency": "Daily"
}