{
  "number": "12812",
  "name": "HATIA - MUMBAI LTT SF Exp",
  "type": "SF",
  "source": "HATIA",
  "sourceCode": "HTE",
  "destination": "LOKMANYA TILAK TERM",
  "destinationCode": "LTT",
  "departureTime": "09:40:00",
  "arrivalTime": "13:35:00",
  "duration": "27h 55m",
  "distance": "1706 km",
  "runningDays": [
    "Mon",
    "Tue",
    "Wed",
    "Thu",
    "Fri",
    "Sat",
    "Sun"
  ],
  "zone": "SER",
  "classes": [
    "3A",
    "2A",
    "SL"
  ],
  "stops": 0,
  "majorStops": [],
  "frequency": "Daily"
}