{
  "number": "13503",
  "name": "Sealdah-Asansol InterCity Express",
  "type": "Exp",
  "source": "KOLKATA SEALDAH",
  "sourceCode": "SDAH",
  "destination": "ASANSOL JN",
  "destinationCode": "ASN",
  "departureTime": "16:40:00",
  "arrivalTime": "20:55:00",
  "duration": "4h 15m",
  "distance": "220 km",
  "runningDays": [
    "Mon",
    "Tue",
    "Wed",
    "Thu",
    "Fri",
    "Sat",
    "Sun"
  ],
  "zone": "ER",
  "classes": [
    "SL",
    "GEN"
  ],
  "stops": 0,
  "majorStops": [],
  "frequency": "Daily"
}