{
  "number": "15015",
  "name": "GORAKHPUR - YESVANTPUR Exp",
  "type": "Exp",
  "source": "GORAKHPUR JN",
  "sourceCode": "GKP",
  "destination": "YESVANTPUR JN",
  "destinationCode": "YPR",
  "departureTime": "06:45:00",
  "arrivalTime": "09:45:00",
  "duration": "51h 0m",
  "distance": "2532 km",
  "runningDays": [
    "Mon",
    "Tue",
    "Wed",
    "Thu",
    "Fri",
    "Sat",
    "Sun"
  ],
  "zone": "NER",
  "classes": [
    "3A",
    "2A",
    "SL"
  ],
  "stops": 0,
  "majorStops": [],
  "frequency": "Daily"
}