{
  "number": "15016",
  "name": "YESVANTPUR - GORAKHPUR Exp",
  "type": "Exp",
  "source": "YESVANTPUR JN",
  "sourceCode": "YPR",
  "destination": "GORAKHPUR JN",
  "destinationCode": "GKP",
  "departureTime": "07:40:00",
  "arrivalTime": "14:20:00",
  "duration": "54h 40m",
  "distance": "2515 km",
  "runningDays": [
    "Mon",
    "Tue",
    "Wed",
    "Thu",
    "Fri",
    "Sat",
    "Sun"
  ],
  "zone": "NER",
  "classes": [
    "3A",
    "2A",
    "SL"
  ],
  "stops": 0,
  "majorStops": [],
  "frequency": "Daily"
}