{
  "number": "16325",
  "name": "Ahilyanagari Express",
  "type": "Exp",
  "source": "INDORE JN BG",
  "sourceCode": "INDB",
  "destination": "TRIVANDRUM CENTRAL",
  "destinationCode": "TVC",
  "departureTime": "16:05:00",
  "arrivalTime": "17:50:00",
  "duration": "49h 45m",
  "distance": "2653 km",
  "runningDays": [
    "Mon",
    "Tue",
    "Wed",
    "Thu",
    "Fri",
    "Sat",
    "Sun"
  ],
  "zone": "SR",
  "classes": [
    "3A",
    "2A",
    "SL"
  ],
  "stops": 0,
  "majorStops": [],
  "frequency": "Daily"
}