{
  "number": "16339",
  "name": "MUMBAI CST - NAGERCOIL Exp",
  "type": "Exp",
  "source": "MUMBAI CST",
  "sourceCode": "CSTM",
  "destination": "NAGERCOIL JN",
  "destinationCode": "NCJ",
  "departureTime": "12:05:00",
  "arrivalTime": "03:15:00",
  "duration": "39h 10m",
  "distance": "1882 km",
  "runningDays": [
    "Mon",
    "Tue",
    "Wed",
    "Thu",
    "Fri",
    "Sat",
    "Sun"
  ],
  "zone": "SR",
  "classes": [
    "3A",
    "2A",
    "SL"
  ],
  "stops": 0,
  "majorStops": [],
  "frequency": "Daily"
}