{
  "number": "17644",
  "name": "Circar Express",
  "type": "Exp",
  "source": "Kakinada Port",
  "sourceCode": "COA",
  "destination": "CHENNAI EGMORE",
  "destinationCode": "MS",
  "departureTime": "14:40:00",
  "arrivalTime": "06:30:00",
  "duration": "15h 50m",
  "distance": "702 km",
  "runningDays": [
    "Mon",
    "Tue",
    "Wed",
    "Thu",
    "Fri",
    "Sat",
    "Sun"
  ],
  "zone": "SCR",
  "classes": [
    "3A",
    "2A",
    "SL"
  ],
  "stops": 0,
  "majorStops": [],
  "frequency": "Daily"
}