{
  "number": "22845",
  "name": "PUNE - HATIA SF Exp",
  "type": "Exp",
  "source": "PUNE JN",
  "sourceCode": "PUNE",
  "destination": "HATIA",
  "destinationCode": "HTE",
  "departureTime": "10:45:00",
  "arrivalTime": "17:10:00",
  "duration": "30h 25m",
  "distance": "1774 km",
  "runningDays": [
    "Mon",
    "Tue",
    "Wed",
    "Thu",
    "Fri",
    "Sat",
    "Sun"
  ],
  "zone": "SER",
  "classes": [
    "3A",
    "2A",
    "SL"
  ],
  "stops": 0,
  "majorStops": [],
  "frequency": "Daily"
}