{
  "number": "52122",
  "name": "Jamner Pachora Passenger",
  "type": "Pass",
  "source": "Jamner",
  "sourceCode": "JMNR",
  "destination": "PACHORA JN",
  "destinationCode": "PC",
  "departureTime": "10:55:00",
  "arrivalTime": "13:10:00",
  "duration": "2h 15m",
  "distance": "56 km",
  "runningDays": [
    "Mon",
    "Tue",
    "Wed",
    "Thu",
    "Fri",
    "Sat",
    "Sun"
  ],
  "zone": "CR",
  "classes": [
    "SL",
    "GEN"
  ],
  "stops": 0,
  "majorStops": [],
  "frequency": "Daily"
}