{
  "number": "53219",
  "name": "Buxar Mughal Sarai Passenger",
  "type": "Pass",
  "source": "BUXAR",
  "sourceCode": "BXR",
  "destination": "MUGHAL SARAI JN",
  "destinationCode": "MGS",
  "departureTime": "23:45:00",
  "arrivalTime": "03:30:00",
  "duration": "3h 45m",
  "distance": "94 km",
  "runningDays": [
    "Mon",
    "Tue",
    "Wed",
    "Thu",
    "Fri",
    "Sat",
    "Sun"
  ],
  "zone": "ECR",
  "classes": [
    "SL",
    "GEN"
  ],
  "stops": 0,
  "majorStops": [],
  "frequency": "Daily"
}