{
  "number": "54002",
  "name": "Rohtak Tilak Bridge Passenger",
  "type": "Pass",
  "source": "ROHTAK JN",
  "sourceCode": "ROK",
  "destination": "TILAK BRIDGE",
  "destinationCode": "TKJ",
  "departureTime": "06:15:00",
  "arrivalTime": "08:44:00",
  "duration": "2h 29m",
  "distance": "73 km",
  "runningDays": [
    "Mon",
    "Tue",
    "Wed",
    "Thu",
    "Fri",
    "Sat",
    "Sun"
  ],
  "zone": "NR",
  "classes": [
    "SL",
    "GEN"
  ],
  "stops": 0,
  "majorStops": [],
  "frequency": "Daily"
}