{
  "number": "54615",
  "name": "Amritsar Pathankot DMU",
  "type": "Pass",
  "source": "AMRITSAR JN",
  "sourceCode": "ASR",
  "destination": "PATHANKOT",
  "destinationCode": "PTK",
  "departureTime": "17:35:00",
  "arrivalTime": "20:50:00",
  "duration": "3h 15m",
  "distance": "107 km",
  "runningDays": [
    "Mon",
    "Tue",
    "Wed",
    "Thu",
    "Fri",
    "Sat",
    "Sun"
  ],
  "zone": "NR",
  "classes": [
    "SL",
    "GEN"
  ],
  "stops": 0,
  "majorStops": [],
  "frequency": "Daily"
}