{
  "number": "63245",
  "name": "Patna Gaya Passenger MEMU",
  "type": "MEMU",
  "source": "PATNA JN",
  "sourceCode": "PNBE",
  "destination": "GAYA JN",
  "destinationCode": "GAYA",
  "departureTime": "08:30:00",
  "arrivalTime": "11:40:00",
  "duration": "3h 10m",
  "distance": "92 km",
  "runningDays": [
    "Mon",
    "Tue",
    "Wed",
    "Thu",
    "Fri",
    "Sat",
    "Sun"
  ],
  "zone": "ECR",
  "classes": [
    "SL",
    "GEN"
  ],
  "stops": 0,
  "majorStops": [],
  "frequency": "Daily"
}